autora/theorist/bsr/__init__.py
autora/theorist/bsr/funcs.py
autora/theorist/bsr/misc.py
autora/theorist/bsr/node.py
autora/theorist/bsr/operation.py
autora/theorist/bsr/prior.py
autora/theorist/bsr/regressor.py
autora_theorist_bsr-1.0.0.dist-info/METADATA
autora_theorist_bsr-1.0.0.dist-info/WHEEL
autora_theorist_bsr-1.0.0.dist-info/top_level.txt
autora_theorist_bsr-1.0.0.dist-info/RECORD
