Metadata-Version: 2.1
Name: autora-theorist-bsr
Version: 1.0.0
Summary: Bayesian Symbolic Regression theorist for AutoRA
Author-email: "Sida (Star) Li" <listar2000@uchicago.edu>
License: MIT License
Project-URL: homepage, http://www.empiricalresearch.ai
Project-URL: repository, https://github.com/AutoResearch/autora-theorist-bsr
Project-URL: documentation, https://autoresearch.github.io/autora/
Requires-Python: <4,>=3.8
Requires-Dist: autora-core
Requires-Dist: scikit-learn
Requires-Dist: scipy
Provides-Extra: dev
Requires-Dist: autora-core[dev] ; extra == 'dev'
